odoo/addons/ssi_lead/README.rst
odoo/addons/ssi_lead/__init__.py
odoo/addons/ssi_lead/__manifest__.py
odoo/addons/ssi_lead/data/ir_sequence_data.xml
odoo/addons/ssi_lead/data/sequence_template_data.xml
odoo/addons/ssi_lead/models/__init__.py
odoo/addons/ssi_lead/models/crm_lead.py
odoo/addons/ssi_lead/static/description/icon.png
odoo/addons/ssi_lead/views/crm_lead_views.xml
odoo14_addon_ssi_lead-14.0.2.2.0.dist-info/METADATA
odoo14_addon_ssi_lead-14.0.2.2.0.dist-info/WHEEL
odoo14_addon_ssi_lead-14.0.2.2.0.dist-info/top_level.txt
odoo14_addon_ssi_lead-14.0.2.2.0.dist-info/RECORD
